{
  "data": {
    "discordMembers": {
      "actual": 20000,
      "display": 20000,
      "human": "20,000"
    },
    "liveryCreators": {
      "actual": 100,
      "display": 100,
      "human": "10"
    },
    "liveries": {
      "actual": 583,
      "display": 580,
      "human": "580"
    },
    "downloads": {
      "actual": 400000,
      "display": 400000,
      "human": "400,000",
      "thousands": 400,
      "thousandsHuman": "400K"
    }
  },
  "keyUrls": {
    "discordInvite": "https://discord.gg/megapack",
    "github": "https://github.com/msfs-mega-pack",
    "managerGithubLatestRelease": "https://github.com/MSFS-Mega-Pack/MSFS2020-livery-manager/releases/latest"
  }
}
